{
  "slug": "petani",
  "name": "Πετανι",
  "centroid_lat": 38.2609789,
  "centroid_lng": 20.3760876,
  "country_code": "GR",
  "admin_level_1": "Ionian Islands",
  "admin_level_2": null,
  "water_body_type": "ocean",
  "substrate_type": "unknown",
  "beach_length_m": null,
  "sources": [
    {
      "source_name": "osm",
      "source_id": "way/303062837",
      "source_url": "https://www.openstreetmap.org/way/303062837"
    },
    {
      "source_name": "osm",
      "source_id": "way/500793729",
      "source_url": "https://www.openstreetmap.org/way/500793729"
    },
    {
      "source_name": "osm",
      "source_id": "way/659810396",
      "source_url": "https://www.openstreetmap.org/way/659810396"
    },
    {
      "source_name": "osm",
      "source_id": "way/659810397",
      "source_url": "https://www.openstreetmap.org/way/659810397"
    },
    {
      "source_name": "osm",
      "source_id": "way/659810398",
      "source_url": "https://www.openstreetmap.org/way/659810398"
    },
    {
      "source_name": "osm",
      "source_id": "way/659810399",
      "source_url": "https://www.openstreetmap.org/way/659810399"
    },
    {
      "source_name": "wikidata",
      "source_id": "Q7171673",
      "source_url": "https://www.wikidata.org/wiki/Q7171673"
    },
    {
      "source_name": "eu_bathing",
      "source_id": "ELBW029120081101",
      "source_url": "https://discomap.eea.europa.eu/Bathingwater/"
    },
    {
      "source_name": "eu_bathing",
      "source_id": "ELBW029120081101",
      "source_url": "https://discomap.eea.europa.eu/Bathingwater/"
    }
  ],
  "attributes": {
    "facilities": {
      "fee_required": false
    },
    "social": {
      "wikipedia_url": "https://en.wikipedia.org/wiki/Petani_Beach"
    },
    "environment": {
      "water_quality_rating": "1 - excellent",
      "eu_bathing_water_type": "Coastal"
    }
  },
  "nearest_city": "Lixouri",
  "nearest_city_distance_km": 8.5,
  "nearest_airport": {
    "iata": "EFL",
    "name": "Kefallinia Airport",
    "distance_km": 19.1
  },
  "safety": {
    "water_quality_rating": "1 - excellent",
    "shark_incidents_total": 0
  },
  "wikipedia_url": "https://en.wikipedia.org/wiki/Petani_Beach",
  "notability_score": 30.3,
  "data_completeness_pct": 25.0,
  "sand": {
    "predicted": {
      "q_pct": 56.8,
      "f_pct": 1.2,
      "l_pct": 42.0,
      "regime": "lithic-rich (volcanic/collisional terrane)",
      "source": "GloPrSM v1.0.0 (IJ_QFL)"
    }
  },
  "waves": {
    "height_mean_m": [
      1.46,
      1.23,
      1.26,
      1.11,
      0.83,
      0.73,
      0.8,
      0.75,
      0.73,
      0.86,
      1.5,
      1.29
    ],
    "height_big_m": [
      2.48,
      2.24,
      2.14,
      1.94,
      1.7,
      1.6,
      1.6,
      1.2,
      1.44,
      1.54,
      3.24,
      2.28
    ],
    "period_mean_s": [
      6.31,
      6.11,
      5.97,
      5.71,
      5.53,
      5.03,
      4.91,
      4.89,
      5.23,
      5.39,
      6.11,
      6.15
    ],
    "summary": {
      "annual_mean_m": 1.05,
      "biggest_month": "Nov",
      "biggest_month_m": 1.5,
      "calmest_month": "Jun",
      "calmest_month_m": 0.73,
      "peak_big_day_m": 3.24,
      "typical_period_s": 5.6,
      "character": "Mixed — usually swimmable, with a livelier season"
    },
    "source": "Open-Meteo Marine (ERA5 Ocean reanalysis, 2023–2024)"
  }
}