{
  "slug": "anse-dumont",
  "name": "ANSE DUMONT",
  "centroid_lat": 16.20182,
  "centroid_lng": -61.45621,
  "country_code": "FR",
  "admin_level_1": null,
  "admin_level_2": null,
  "water_body_type": "ocean",
  "substrate_type": "unknown",
  "beach_length_m": null,
  "sources": [
    {
      "source_name": "wikidata",
      "source_id": "Q118719878",
      "source_url": "https://www.wikidata.org/wiki/Q118719878"
    },
    {
      "source_name": "eu_bathing",
      "source_id": "FRY1097113M971146",
      "source_url": "https://discomap.eea.europa.eu/Bathingwater/"
    },
    {
      "source_name": "eu_bathing",
      "source_id": "FRY1097113M971146",
      "source_url": "https://discomap.eea.europa.eu/Bathingwater/"
    }
  ],
  "attributes": {
    "social": {
      "image_url": "http://commons.wikimedia.org/wiki/Special:FilePath/Anse%20du%20Mont.jpg"
    },
    "environment": {
      "water_quality_rating": "1 - excellent",
      "eu_bathing_water_type": "Coastal"
    }
  }
}