{
  "slug": "balneario-do-chico-periquito",
  "name": "Balneário do Chico Periquito",
  "centroid_lat": -9.4438205,
  "centroid_lng": -40.8103077,
  "country_code": null,
  "admin_level_1": null,
  "admin_level_2": null,
  "water_body_type": "ocean",
  "substrate_type": "sand",
  "beach_length_m": null,
  "sources": [
    {
      "source_name": "osm",
      "source_id": "way/219968632",
      "source_url": "https://www.openstreetmap.org/way/219968632"
    }
  ],
  "attributes": {
    "facilities": {
      "access": "yes"
    }
  }
}