{
  "slug": "beach-37.8119-24.8275",
  "name": null,
  "centroid_lat": 37.8119205,
  "centroid_lng": 24.8275122,
  "country_code": null,
  "admin_level_1": null,
  "admin_level_2": null,
  "water_body_type": "ocean",
  "substrate_type": "unknown",
  "beach_length_m": null,
  "sources": [
    {
      "source_name": "osm",
      "source_id": "way/715061313",
      "source_url": "https://www.openstreetmap.org/way/715061313"
    },
    {
      "source_name": "osm",
      "source_id": "way/715061314",
      "source_url": "https://www.openstreetmap.org/way/715061314"
    }
  ],
  "attributes": {}
}