{
  "slug": "beach-66.0725-30.8781",
  "name": null,
  "centroid_lat": 66.0724582,
  "centroid_lng": 30.8781003,
  "country_code": null,
  "admin_level_1": null,
  "admin_level_2": null,
  "water_body_type": "ocean",
  "substrate_type": "unknown",
  "beach_length_m": null,
  "sources": [
    {
      "source_name": "osm",
      "source_id": "relation/19651386",
      "source_url": "https://www.openstreetmap.org/relation/19651386"
    },
    {
      "source_name": "osm",
      "source_id": "relation/19651395",
      "source_url": "https://www.openstreetmap.org/relation/19651395"
    },
    {
      "source_name": "osm",
      "source_id": "relation/19651396",
      "source_url": "https://www.openstreetmap.org/relation/19651396"
    }
  ],
  "attributes": {}
}