{
  "slug": "beach-37.2429-126.5012",
  "name": null,
  "centroid_lat": 37.2428773,
  "centroid_lng": 126.5012187,
  "country_code": null,
  "admin_level_1": null,
  "admin_level_2": null,
  "water_body_type": "ocean",
  "substrate_type": "unknown",
  "beach_length_m": null,
  "sources": [
    {
      "source_name": "osm",
      "source_id": "way/1416486692",
      "source_url": "https://www.openstreetmap.org/way/1416486692"
    },
    {
      "source_name": "osm",
      "source_id": "way/1416486695",
      "source_url": "https://www.openstreetmap.org/way/1416486695"
    }
  ],
  "attributes": {}
}