{
  "slug": "beach-63.4291-35.2147",
  "name": null,
  "centroid_lat": 63.4291302,
  "centroid_lng": 35.2146631,
  "country_code": null,
  "admin_level_1": null,
  "admin_level_2": null,
  "water_body_type": "ocean",
  "substrate_type": "sand",
  "beach_length_m": null,
  "sources": [
    {
      "source_name": "osm",
      "source_id": "relation/10017415",
      "source_url": "https://www.openstreetmap.org/relation/10017415"
    },
    {
      "source_name": "osm",
      "source_id": "relation/10017417",
      "source_url": "https://www.openstreetmap.org/relation/10017417"
    }
  ],
  "attributes": {}
}