{
  "slug": "beach-9.5833-125.7582",
  "name": null,
  "centroid_lat": 9.5833307,
  "centroid_lng": 125.7582202,
  "country_code": null,
  "admin_level_1": null,
  "admin_level_2": null,
  "water_body_type": "ocean",
  "substrate_type": "unknown",
  "beach_length_m": null,
  "sources": [
    {
      "source_name": "osm",
      "source_id": "way/448890571",
      "source_url": "https://www.openstreetmap.org/way/448890571"
    },
    {
      "source_name": "osm",
      "source_id": "way/448900697",
      "source_url": "https://www.openstreetmap.org/way/448900697"
    },
    {
      "source_name": "osm",
      "source_id": "way/448900698",
      "source_url": "https://www.openstreetmap.org/way/448900698"
    }
  ],
  "attributes": {}
}