{
  "slug": "beach-48.7710--86.4462",
  "name": null,
  "centroid_lat": 48.770973,
  "centroid_lng": -86.4462445,
  "country_code": null,
  "admin_level_1": null,
  "admin_level_2": null,
  "water_body_type": "ocean",
  "substrate_type": "pebble",
  "beach_length_m": null,
  "sources": [
    {
      "source_name": "osm",
      "source_id": "way/1132580680",
      "source_url": "https://www.openstreetmap.org/way/1132580680"
    }
  ],
  "attributes": {
    "safety": {
      "lifeguard": false
    }
  }
}