{
  "slug": "beach-65.7544-33.5786",
  "name": null,
  "centroid_lat": 65.7544286,
  "centroid_lng": 33.5785781,
  "country_code": null,
  "admin_level_1": null,
  "admin_level_2": null,
  "water_body_type": "ocean",
  "substrate_type": "sand",
  "beach_length_m": null,
  "sources": [
    {
      "source_name": "osm",
      "source_id": "relation/5461552",
      "source_url": "https://www.openstreetmap.org/relation/5461552"
    },
    {
      "source_name": "osm",
      "source_id": "relation/5461553",
      "source_url": "https://www.openstreetmap.org/relation/5461553"
    },
    {
      "source_name": "osm",
      "source_id": "relation/5461615",
      "source_url": "https://www.openstreetmap.org/relation/5461615"
    }
  ],
  "attributes": {}
}