{
  "slug": "beach-36.0210-27.7564",
  "name": null,
  "centroid_lat": 36.0209992,
  "centroid_lng": 27.7563702,
  "country_code": null,
  "admin_level_1": null,
  "admin_level_2": null,
  "water_body_type": "ocean",
  "substrate_type": "pebble",
  "beach_length_m": null,
  "sources": [
    {
      "source_name": "osm",
      "source_id": "way/280195845",
      "source_url": "https://www.openstreetmap.org/way/280195845"
    }
  ],
  "attributes": {
    "facilities": {
      "access": "yes"
    }
  }
}