{
  "slug": "beach-47.7212--3.9564",
  "name": null,
  "centroid_lat": 47.721232,
  "centroid_lng": -3.956428,
  "country_code": null,
  "admin_level_1": null,
  "admin_level_2": null,
  "water_body_type": "ocean",
  "substrate_type": "sand",
  "beach_length_m": null,
  "sources": [
    {
      "source_name": "osm",
      "source_id": "relation/6480094",
      "source_url": "https://www.openstreetmap.org/relation/6480094"
    }
  ],
  "attributes": {
    "facilities": {
      "access": "yes"
    }
  }
}