{
  "slug": "beach-52.4104-15.4630",
  "name": null,
  "centroid_lat": 52.4104065,
  "centroid_lng": 15.4629662,
  "country_code": null,
  "admin_level_1": null,
  "admin_level_2": null,
  "water_body_type": "ocean",
  "substrate_type": "unknown",
  "beach_length_m": null,
  "sources": [
    {
      "source_name": "osm",
      "source_id": "way/338874547",
      "source_url": "https://www.openstreetmap.org/way/338874547"
    },
    {
      "source_name": "osm",
      "source_id": "way/446575218",
      "source_url": "https://www.openstreetmap.org/way/446575218"
    }
  ],
  "attributes": {}
}