{
  "slug": "beach-61.5470--6.8148",
  "name": null,
  "centroid_lat": 61.5470076,
  "centroid_lng": -6.8147965,
  "country_code": null,
  "admin_level_1": null,
  "admin_level_2": null,
  "water_body_type": "ocean",
  "substrate_type": "unknown",
  "beach_length_m": null,
  "sources": [
    {
      "source_name": "osm",
      "source_id": "way/1357806278",
      "source_url": "https://www.openstreetmap.org/way/1357806278"
    },
    {
      "source_name": "osm",
      "source_id": "way/1357806279",
      "source_url": "https://www.openstreetmap.org/way/1357806279"
    },
    {
      "source_name": "osm",
      "source_id": "way/1357806280",
      "source_url": "https://www.openstreetmap.org/way/1357806280"
    }
  ],
  "attributes": {}
}