{
  "slug": "beach--20.3705-115.5193",
  "name": null,
  "centroid_lat": -20.3704992,
  "centroid_lng": 115.5192903,
  "country_code": null,
  "admin_level_1": null,
  "admin_level_2": null,
  "water_body_type": "ocean",
  "substrate_type": "sand",
  "beach_length_m": null,
  "sources": [
    {
      "source_name": "osm",
      "source_id": "way/1422818681",
      "source_url": "https://www.openstreetmap.org/way/1422818681"
    },
    {
      "source_name": "osm",
      "source_id": "way/1422818682",
      "source_url": "https://www.openstreetmap.org/way/1422818682"
    },
    {
      "source_name": "osm",
      "source_id": "way/1422818683",
      "source_url": "https://www.openstreetmap.org/way/1422818683"
    },
    {
      "source_name": "osm",
      "source_id": "way/1422818684",
      "source_url": "https://www.openstreetmap.org/way/1422818684"
    },
    {
      "source_name": "osm",
      "source_id": "way/1422818685",
      "source_url": "https://www.openstreetmap.org/way/1422818685"
    },
    {
      "source_name": "osm",
      "source_id": "way/1422818686",
      "source_url": "https://www.openstreetmap.org/way/1422818686"
    },
    {
      "source_name": "osm",
      "source_id": "way/1422818699",
      "source_url": "https://www.openstreetmap.org/way/1422818699"
    },
    {
      "source_name": "osm",
      "source_id": "way/1422818700",
      "source_url": "https://www.openstreetmap.org/way/1422818700"
    },
    {
      "source_name": "osm",
      "source_id": "way/1422818701",
      "source_url": "https://www.openstreetmap.org/way/1422818701"
    },
    {
      "source_name": "osm",
      "source_id": "way/1422818702",
      "source_url": "https://www.openstreetmap.org/way/1422818702"
    }
  ],
  "attributes": {}
}