{
  "slug": "beach-42.7064-27.7716",
  "name": null,
  "centroid_lat": 42.706413,
  "centroid_lng": 27.7715923,
  "country_code": null,
  "admin_level_1": null,
  "admin_level_2": null,
  "water_body_type": "ocean",
  "substrate_type": "sand",
  "beach_length_m": null,
  "sources": [
    {
      "source_name": "osm",
      "source_id": "way/220774435",
      "source_url": "https://www.openstreetmap.org/way/220774435"
    }
  ],
  "attributes": {
    "facilities": {
      "access": "yes"
    }
  }
}