{
  "slug": "beach--17.9630--38.7054",
  "name": null,
  "centroid_lat": -17.9630027,
  "centroid_lng": -38.7054423,
  "country_code": null,
  "admin_level_1": null,
  "admin_level_2": null,
  "water_body_type": "ocean",
  "substrate_type": "unknown",
  "beach_length_m": null,
  "sources": [
    {
      "source_name": "osm",
      "source_id": "way/666218876",
      "source_url": "https://www.openstreetmap.org/way/666218876"
    },
    {
      "source_name": "osm",
      "source_id": "way/666807579",
      "source_url": "https://www.openstreetmap.org/way/666807579"
    }
  ],
  "attributes": {}
}