{
  "slug": "beach-52.2553-6.1449",
  "name": null,
  "centroid_lat": 52.255286,
  "centroid_lng": 6.1448764,
  "country_code": null,
  "admin_level_1": null,
  "admin_level_2": null,
  "water_body_type": "ocean",
  "substrate_type": "unknown",
  "beach_length_m": null,
  "sources": [
    {
      "source_name": "osm",
      "source_id": "way/60298125",
      "source_url": "https://www.openstreetmap.org/way/60298125"
    },
    {
      "source_name": "osm",
      "source_id": "way/60298227",
      "source_url": "https://www.openstreetmap.org/way/60298227"
    },
    {
      "source_name": "osm",
      "source_id": "way/60298341",
      "source_url": "https://www.openstreetmap.org/way/60298341"
    },
    {
      "source_name": "osm",
      "source_id": "way/60298426",
      "source_url": "https://www.openstreetmap.org/way/60298426"
    },
    {
      "source_name": "osm",
      "source_id": "way/60298549",
      "source_url": "https://www.openstreetmap.org/way/60298549"
    },
    {
      "source_name": "osm",
      "source_id": "way/60298598",
      "source_url": "https://www.openstreetmap.org/way/60298598"
    },
    {
      "source_name": "osm",
      "source_id": "way/60298780",
      "source_url": "https://www.openstreetmap.org/way/60298780"
    },
    {
      "source_name": "osm",
      "source_id": "way/60298921",
      "source_url": "https://www.openstreetmap.org/way/60298921"
    },
    {
      "source_name": "osm",
      "source_id": "way/60298962",
      "source_url": "https://www.openstreetmap.org/way/60298962"
    },
    {
      "source_name": "osm",
      "source_id": "way/60299077",
      "source_url": "https://www.openstreetmap.org/way/60299077"
    },
    {
      "source_name": "osm",
      "source_id": "way/60299228",
      "source_url": "https://www.openstreetmap.org/way/60299228"
    },
    {
      "source_name": "osm",
      "source_id": "way/60299789",
      "source_url": "https://www.openstreetmap.org/way/60299789"
    },
    {
      "source_name": "osm",
      "source_id": "way/60300052",
      "source_url": "https://www.openstreetmap.org/way/60300052"
    },
    {
      "source_name": "osm",
      "source_id": "way/60300173",
      "source_url": "https://www.openstreetmap.org/way/60300173"
    },
    {
      "source_name": "osm",
      "source_id": "way/60300256",
      "source_url": "https://www.openstreetmap.org/way/60300256"
    }
  ],
  "attributes": {}
}