{
  "slug": "beach-44.6173--67.3105",
  "name": null,
  "centroid_lat": 44.6173331,
  "centroid_lng": -67.3105053,
  "country_code": null,
  "admin_level_1": null,
  "admin_level_2": null,
  "water_body_type": "ocean",
  "substrate_type": "gravel",
  "beach_length_m": null,
  "sources": [
    {
      "source_name": "osm",
      "source_id": "relation/14648584",
      "source_url": "https://www.openstreetmap.org/relation/14648584"
    },
    {
      "source_name": "osm",
      "source_id": "relation/14648591",
      "source_url": "https://www.openstreetmap.org/relation/14648591"
    },
    {
      "source_name": "osm",
      "source_id": "relation/14648592",
      "source_url": "https://www.openstreetmap.org/relation/14648592"
    }
  ],
  "attributes": {}
}