{
  "slug": "beach-53.5429--2.2955",
  "name": null,
  "centroid_lat": 53.542924,
  "centroid_lng": -2.2954948,
  "country_code": null,
  "admin_level_1": null,
  "admin_level_2": null,
  "water_body_type": "ocean",
  "substrate_type": "unknown",
  "beach_length_m": null,
  "sources": [
    {
      "source_name": "osm",
      "source_id": "way/360399125",
      "source_url": "https://www.openstreetmap.org/way/360399125"
    },
    {
      "source_name": "osm",
      "source_id": "way/360399153",
      "source_url": "https://www.openstreetmap.org/way/360399153"
    }
  ],
  "attributes": {}
}