{
  "slug": "beach-50.5252-30.5707",
  "name": null,
  "centroid_lat": 50.5252368,
  "centroid_lng": 30.5707231,
  "country_code": null,
  "admin_level_1": null,
  "admin_level_2": null,
  "water_body_type": "ocean",
  "substrate_type": "unknown",
  "beach_length_m": null,
  "sources": [
    {
      "source_name": "osm",
      "source_id": "way/946779362",
      "source_url": "https://www.openstreetmap.org/way/946779362"
    },
    {
      "source_name": "osm",
      "source_id": "way/949117591",
      "source_url": "https://www.openstreetmap.org/way/949117591"
    }
  ],
  "attributes": {}
}