{
  "slug": "beach-8.2591-98.6303",
  "name": null,
  "centroid_lat": 8.259068,
  "centroid_lng": 98.630286,
  "country_code": null,
  "admin_level_1": null,
  "admin_level_2": null,
  "water_body_type": "ocean",
  "substrate_type": "sand",
  "beach_length_m": null,
  "sources": [
    {
      "source_name": "osm",
      "source_id": "way/703233064",
      "source_url": "https://www.openstreetmap.org/way/703233064"
    },
    {
      "source_name": "osm",
      "source_id": "way/703233065",
      "source_url": "https://www.openstreetmap.org/way/703233065"
    }
  ],
  "attributes": {}
}