{
  "slug": "beach-57.3662--6.5255",
  "name": null,
  "centroid_lat": 57.3662443,
  "centroid_lng": -6.5254595,
  "country_code": null,
  "admin_level_1": null,
  "admin_level_2": null,
  "water_body_type": "ocean",
  "substrate_type": "unknown",
  "beach_length_m": null,
  "sources": [
    {
      "source_name": "osm",
      "source_id": "way/384141457",
      "source_url": "https://www.openstreetmap.org/way/384141457"
    },
    {
      "source_name": "osm",
      "source_id": "way/519422536",
      "source_url": "https://www.openstreetmap.org/way/519422536"
    }
  ],
  "attributes": {}
}