{
  "slug": "beach-49.8844-36.0415",
  "name": null,
  "centroid_lat": 49.8843763,
  "centroid_lng": 36.0414936,
  "country_code": null,
  "admin_level_1": null,
  "admin_level_2": null,
  "water_body_type": "ocean",
  "substrate_type": "sand",
  "beach_length_m": null,
  "sources": [
    {
      "source_name": "osm",
      "source_id": "way/744287191",
      "source_url": "https://www.openstreetmap.org/way/744287191"
    },
    {
      "source_name": "osm",
      "source_id": "way/744287192",
      "source_url": "https://www.openstreetmap.org/way/744287192"
    },
    {
      "source_name": "osm",
      "source_id": "way/744287193",
      "source_url": "https://www.openstreetmap.org/way/744287193"
    },
    {
      "source_name": "osm",
      "source_id": "way/949327164",
      "source_url": "https://www.openstreetmap.org/way/949327164"
    }
  ],
  "attributes": {}
}