{
  "slug": "cabo-de-santa-maria",
  "name": "Cabo de Santa Maria",
  "centroid_lat": 16.202,
  "centroid_lng": -22.865,
  "country_code": null,
  "admin_level_1": null,
  "admin_level_2": null,
  "water_body_type": "ocean",
  "substrate_type": "unknown",
  "beach_length_m": null,
  "sources": [
    {
      "source_name": "wikidata",
      "source_id": "Q8254536",
      "source_url": "https://www.wikidata.org/wiki/Q8254536"
    }
  ],
  "attributes": {
    "social": {
      "wikipedia_url": "https://en.wikipedia.org/wiki/Praia_de_Atalanta"
    }
  }
}