{
  "slug": "elechol-ra-ngerikl",
  "name": "Elechol Ra Ngerikl",
  "centroid_lat": 7.0033105,
  "centroid_lng": 134.2599838,
  "country_code": null,
  "admin_level_1": null,
  "admin_level_2": null,
  "water_body_type": "ocean",
  "substrate_type": "unknown",
  "beach_length_m": null,
  "sources": [
    {
      "source_name": "osm",
      "source_id": "node/357256053",
      "source_url": "https://www.openstreetmap.org/node/357256053"
    },
    {
      "source_name": "osm",
      "source_id": "relation/13843827",
      "source_url": "https://www.openstreetmap.org/relation/13843827"
    }
  ],
  "attributes": {}
}