{
  "slug": "fox-island-sand-spit",
  "name": "Fox Island Sand Spit",
  "centroid_lat": 47.2779499,
  "centroid_lng": -122.6655631,
  "country_code": null,
  "admin_level_1": null,
  "admin_level_2": null,
  "water_body_type": "ocean",
  "substrate_type": "sand",
  "beach_length_m": null,
  "sources": [
    {
      "source_name": "osm",
      "source_id": "way/422551942",
      "source_url": "https://www.openstreetmap.org/way/422551942"
    }
  ],
  "attributes": {
    "facilities": {
      "access": "yes"
    }
  }
}