{
  "slug": "kapielisko-nr-1-zoom-natury",
  "name": "KĄPIELISKO NR 1 ZOOM NATURY",
  "centroid_lat": 50.69252,
  "centroid_lng": 22.39974,
  "country_code": "PL",
  "admin_level_1": null,
  "admin_level_2": null,
  "water_body_type": "lake",
  "substrate_type": "unknown",
  "beach_length_m": null,
  "sources": [
    {
      "source_name": "osm",
      "source_id": "way/338617984",
      "source_url": "https://www.openstreetmap.org/way/338617984"
    },
    {
      "source_name": "osm",
      "source_id": "way/575645210",
      "source_url": "https://www.openstreetmap.org/way/575645210"
    },
    {
      "source_name": "eu_bathing",
      "source_id": "PL3130505406000004",
      "source_url": "https://discomap.eea.europa.eu/Bathingwater/"
    },
    {
      "source_name": "eu_bathing",
      "source_id": "PL3130505406000004",
      "source_url": "https://discomap.eea.europa.eu/Bathingwater/"
    }
  ],
  "attributes": {
    "environment": {
      "water_quality_rating": "0 - not classified",
      "eu_bathing_water_type": "Lake"
    }
  }
}