{
  "slug": "kollevag-badestrand",
  "name": "Kollevåg badestrand",
  "centroid_lat": 60.4512402,
  "centroid_lng": 5.1103259,
  "country_code": null,
  "admin_level_1": null,
  "admin_level_2": null,
  "water_body_type": "ocean",
  "substrate_type": "sand",
  "beach_length_m": null,
  "sources": [
    {
      "source_name": "osm",
      "source_id": "way/162891833",
      "source_url": "https://www.openstreetmap.org/way/162891833"
    },
    {
      "source_name": "osm",
      "source_id": "way/732991959",
      "source_url": "https://www.openstreetmap.org/way/732991959"
    },
    {
      "source_name": "osm",
      "source_id": "way/896293882",
      "source_url": "https://www.openstreetmap.org/way/896293882"
    }
  ],
  "attributes": {
    "safety": {
      "lifeguard": false
    }
  }
}