{
  "slug": "la-cuvette-beach",
  "name": "La Cuvette Beach",
  "centroid_lat": -20.00714,
  "centroid_lng": 57.57807,
  "country_code": null,
  "admin_level_1": null,
  "admin_level_2": null,
  "water_body_type": "ocean",
  "substrate_type": "unknown",
  "beach_length_m": null,
  "sources": [
    {
      "source_name": "wikidata",
      "source_id": "Q124454173",
      "source_url": "https://www.wikidata.org/wiki/Q124454173"
    }
  ],
  "attributes": {
    "social": {
      "image_url": "http://commons.wikimedia.org/wiki/Special:FilePath/Grand%20Baie%2C%20La%20Cuvette%20Beach.jpg"
    }
  }
}