{
  "slug": "lido-panfilo",
  "name": "Lido Panfilo",
  "centroid_lat": 42.0045652,
  "centroid_lng": 14.9935983,
  "country_code": null,
  "admin_level_1": null,
  "admin_level_2": null,
  "water_body_type": "ocean",
  "substrate_type": "unknown",
  "beach_length_m": null,
  "sources": [
    {
      "source_name": "osm",
      "source_id": "way/1076684934",
      "source_url": "https://www.openstreetmap.org/way/1076684934"
    }
  ],
  "attributes": {
    "social": {
      "dog_friendly": "leashed"
    },
    "facilities": {
      "fee_required": false
    }
  }
}