{
  "slug": "north-beach-72",
  "name": "North Beach",
  "centroid_lat": -46.3518021,
  "centroid_lng": 168.0332813,
  "country_code": null,
  "admin_level_1": null,
  "admin_level_2": null,
  "water_body_type": "ocean",
  "substrate_type": "unknown",
  "beach_length_m": null,
  "sources": [
    {
      "source_name": "osm",
      "source_id": "way/1257087616",
      "source_url": "https://www.openstreetmap.org/way/1257087616"
    },
    {
      "source_name": "wikidata",
      "source_id": "Q32299667",
      "source_url": "https://www.wikidata.org/wiki/Q32299667"
    }
  ],
  "attributes": {}
}