{
  "slug": "paul-s-beach",
  "name": "Paul's Beach",
  "centroid_lat": 40.4626888,
  "centroid_lng": -74.2559394,
  "country_code": null,
  "admin_level_1": null,
  "admin_level_2": null,
  "water_body_type": "ocean",
  "substrate_type": "unknown",
  "beach_length_m": null,
  "sources": [
    {
      "source_name": "osm",
      "source_id": "way/945779338",
      "source_url": "https://www.openstreetmap.org/way/945779338"
    },
    {
      "source_name": "osm",
      "source_id": "relation/17770691",
      "source_url": "https://www.openstreetmap.org/relation/17770691"
    }
  ],
  "attributes": {}
}