{
  "slug": "plage-du-grand-crohot",
  "name": "Plage du Grand Crohot",
  "centroid_lat": 44.798849,
  "centroid_lng": -1.2343628,
  "country_code": null,
  "admin_level_1": null,
  "admin_level_2": null,
  "water_body_type": "ocean",
  "substrate_type": "sand",
  "beach_length_m": null,
  "sources": [
    {
      "source_name": "osm",
      "source_id": "node/4988153101",
      "source_url": "https://www.openstreetmap.org/node/4988153101"
    },
    {
      "source_name": "eu_bathing",
      "source_id": "FRI1233236M033060",
      "source_url": "https://discomap.eea.europa.eu/Bathingwater/"
    },
    {
      "source_name": "eu_bathing",
      "source_id": "FRI1233236M033060",
      "source_url": "https://discomap.eea.europa.eu/Bathingwater/"
    }
  ],
  "attributes": {
    "environment": {
      "water_quality_rating": "1 - excellent",
      "eu_bathing_water_type": "Coastal"
    }
  }
}