{
  "slug": "playa-el-cable-rio-real-pm1",
  "name": "PLAYA  EL CABLE-RIO REAL PM1",
  "centroid_lat": 36.5067,
  "centroid_lng": -4.8565,
  "country_code": "ES",
  "admin_level_1": null,
  "admin_level_2": null,
  "water_body_type": "ocean",
  "substrate_type": "unknown",
  "beach_length_m": null,
  "sources": [
    {
      "source_name": "osm",
      "source_id": "way/1302058739",
      "source_url": "https://www.openstreetmap.org/way/1302058739"
    },
    {
      "source_name": "osm",
      "source_id": "way/1302058740",
      "source_url": "https://www.openstreetmap.org/way/1302058740"
    },
    {
      "source_name": "eu_bathing",
      "source_id": "ES617M0691553",
      "source_url": "https://discomap.eea.europa.eu/Bathingwater/"
    },
    {
      "source_name": "eu_bathing",
      "source_id": "ES617M0691553",
      "source_url": "https://discomap.eea.europa.eu/Bathingwater/"
    }
  ],
  "attributes": {
    "facilities": {
      "fee_required": true
    },
    "environment": {
      "water_quality_rating": "1 - excellent",
      "eu_bathing_water_type": "Coastal"
    }
  }
}