{
  "slug": "playa-de-los-lances-1",
  "name": "Playa de Los Lances",
  "centroid_lat": 36.03994,
  "centroid_lng": -5.63453,
  "country_code": null,
  "admin_level_1": null,
  "admin_level_2": null,
  "water_body_type": "ocean",
  "substrate_type": "unknown",
  "beach_length_m": null,
  "sources": [
    {
      "source_name": "wikidata",
      "source_id": "Q5102776",
      "source_url": "https://www.wikidata.org/wiki/Q5102776"
    }
  ],
  "attributes": {
    "social": {
      "image_url": "http://commons.wikimedia.org/wiki/Special:FilePath/Bunker-2.jpg",
      "wikipedia_url": "https://en.wikipedia.org/wiki/Playa_de_Los_Lances"
    }
  }
}