{
  "slug": "praia-de-carquejinha",
  "name": "Praia de Carquejinha",
  "centroid_lat": 15.976,
  "centroid_lng": -22.855,
  "country_code": null,
  "admin_level_1": null,
  "admin_level_2": null,
  "water_body_type": "ocean",
  "substrate_type": "unknown",
  "beach_length_m": null,
  "sources": [
    {
      "source_name": "wikidata",
      "source_id": "Q55630354",
      "source_url": "https://www.wikidata.org/wiki/Q55630354"
    }
  ],
  "attributes": {
    "social": {
      "wikipedia_url": "https://en.wikipedia.org/wiki/Praia_de_Carquejinha"
    }
  }
}