{
  "slug": "praia-quarto-crescente",
  "name": "Praia Quarto Crescente",
  "centroid_lat": -15.8926274,
  "centroid_lng": -52.2503945,
  "country_code": null,
  "admin_level_1": null,
  "admin_level_2": null,
  "water_body_type": "ocean",
  "substrate_type": "unknown",
  "beach_length_m": null,
  "sources": [
    {
      "source_name": "osm",
      "source_id": "node/2827690221",
      "source_url": "https://www.openstreetmap.org/node/2827690221"
    },
    {
      "source_name": "osm",
      "source_id": "way/276132829",
      "source_url": "https://www.openstreetmap.org/way/276132829"
    }
  ],
  "attributes": {}
}