{
  "slug": "raymen-beach-resort",
  "name": "Raymen Beach Resort",
  "centroid_lat": 10.5340748,
  "centroid_lng": 122.5173707,
  "country_code": null,
  "admin_level_1": null,
  "admin_level_2": null,
  "water_body_type": "ocean",
  "substrate_type": "unknown",
  "beach_length_m": null,
  "sources": [
    {
      "source_name": "osm",
      "source_id": "node/4210878550",
      "source_url": "https://www.openstreetmap.org/node/4210878550"
    },
    {
      "source_name": "osm",
      "source_id": "node/4210878551",
      "source_url": "https://www.openstreetmap.org/node/4210878551"
    },
    {
      "source_name": "osm",
      "source_id": "node/4210878552",
      "source_url": "https://www.openstreetmap.org/node/4210878552"
    },
    {
      "source_name": "osm",
      "source_id": "node/4578643589",
      "source_url": "https://www.openstreetmap.org/node/4578643589"
    },
    {
      "source_name": "osm",
      "source_id": "way/246818191",
      "source_url": "https://www.openstreetmap.org/way/246818191"
    }
  ],
  "attributes": {}
}