{
  "slug": "spiaggia-di-civitavecchia",
  "name": "Spiaggia di Civitavecchia",
  "centroid_lat": 42.0882,
  "centroid_lng": 11.79456,
  "country_code": null,
  "admin_level_1": null,
  "admin_level_2": null,
  "water_body_type": "ocean",
  "substrate_type": "unknown",
  "beach_length_m": null,
  "sources": [
    {
      "source_name": "osm",
      "source_id": "way/373794829",
      "source_url": "https://www.openstreetmap.org/way/373794829"
    },
    {
      "source_name": "wikidata",
      "source_id": "Q33337304",
      "source_url": "https://www.wikidata.org/wiki/Q33337304"
    }
  ],
  "attributes": {}
}