{
  "slug": "thurstaston-beach",
  "name": "Thurstaston Beach",
  "centroid_lat": 53.33731,
  "centroid_lng": -3.14235,
  "country_code": null,
  "admin_level_1": null,
  "admin_level_2": null,
  "water_body_type": "ocean",
  "substrate_type": "unknown",
  "beach_length_m": null,
  "sources": [
    {
      "source_name": "wikidata",
      "source_id": "Q31845081",
      "source_url": "https://www.wikidata.org/wiki/Q31845081"
    }
  ],
  "attributes": {
    "social": {
      "image_url": "http://commons.wikimedia.org/wiki/Special:FilePath/Thurstaston%20beach%20-%20IMG%200859.JPG"
    }
  }
}