{
  "slug": "tombolo-di-bolgheri",
  "name": "TOMBOLO DI BOLGHERI",
  "centroid_lat": 43.2104,
  "centroid_lng": 10.5321,
  "country_code": "IT",
  "admin_level_1": null,
  "admin_level_2": null,
  "water_body_type": "ocean",
  "substrate_type": "unknown",
  "beach_length_m": null,
  "sources": [
    {
      "source_name": "eu_bathing",
      "source_id": "IT009049006010",
      "source_url": "https://discomap.eea.europa.eu/Bathingwater/"
    },
    {
      "source_name": "eu_bathing",
      "source_id": "IT009049006010",
      "source_url": "https://discomap.eea.europa.eu/Bathingwater/"
    }
  ],
  "attributes": {
    "environment": {
      "water_quality_rating": "1 - excellent",
      "eu_bathing_water_type": "Coastal"
    }
  }
}