{
  "slug": "vancouver-beach-1",
  "name": "Vancouver Beach",
  "centroid_lat": -35.063333333,
  "centroid_lng": 117.917222222,
  "country_code": null,
  "admin_level_1": null,
  "admin_level_2": null,
  "water_body_type": "ocean",
  "substrate_type": "unknown",
  "beach_length_m": null,
  "sources": [
    {
      "source_name": "wikidata",
      "source_id": "Q21895565",
      "source_url": "https://www.wikidata.org/wiki/Q21895565"
    }
  ],
  "attributes": {
    "social": {
      "image_url": "http://commons.wikimedia.org/wiki/Special:FilePath/Vancouver%20Beach%20Western%20Australia.jpg"
    }
  }
}