{
  "slug": "wassenaarse-slag-1",
  "name": "WASSENAARSE SLAG",
  "centroid_lat": 52.16243,
  "centroid_lng": 4.34515,
  "country_code": "NL",
  "admin_level_1": null,
  "admin_level_2": null,
  "water_body_type": "ocean",
  "substrate_type": "unknown",
  "beach_length_m": null,
  "sources": [
    {
      "source_name": "wikidata",
      "source_id": "Q2667949",
      "source_url": "https://www.wikidata.org/wiki/Q2667949"
    },
    {
      "source_name": "eu_bathing",
      "source_id": "NLBW95_WASSNSSBSD",
      "source_url": "https://discomap.eea.europa.eu/Bathingwater/"
    },
    {
      "source_name": "eu_bathing",
      "source_id": "NLBW95_WASSNSSBSD",
      "source_url": "https://discomap.eea.europa.eu/Bathingwater/"
    }
  ],
  "attributes": {
    "social": {
      "image_url": "http://commons.wikimedia.org/wiki/Special:FilePath/Strandopgang%20Wassenaarse%20Slag%20P1290261.jpg"
    },
    "environment": {
      "water_quality_rating": "2 - good",
      "eu_bathing_water_type": "Coastal"
    }
  }
}