{
  "slug": "whareakeake",
  "name": "Whareakeake",
  "centroid_lat": -45.7625729,
  "centroid_lng": 170.6692704,
  "country_code": null,
  "admin_level_1": null,
  "admin_level_2": null,
  "water_body_type": "ocean",
  "substrate_type": "sand",
  "beach_length_m": null,
  "sources": [
    {
      "source_name": "osm",
      "source_id": "way/281487447",
      "source_url": "https://www.openstreetmap.org/way/281487447"
    },
    {
      "source_name": "wikidata",
      "source_id": "Q49325281",
      "source_url": "https://www.wikidata.org/wiki/Q49325281"
    }
  ],
  "attributes": {
    "social": {
      "wikipedia_url": "https://en.wikipedia.org/wiki/Whareakeake"
    }
  }
}