{
  "slug": "ipanema-district",
  "beach_name": "Ipanema",
  "version": "0.9",
  "tier": 2,
  "subtitle": "The two kilometers of Rio sand that a 1962 bossa nova song made into a place the whole world thinks it knows.",
  "spike_statement": "The beach a 1962 bossa nova song made famous, sorted into numbered lifeguard-post tribes under the granite of Dois Irmãos.",
  "levers": {
    "primary_color": "#C9A24B",
    "supporting_color": "#1F5C6B",
    "hero_type": "MONUMENT",
    "display_pairing": "CLASSICAL",
    "voice_register": "ROMANTIC",
    "photo_tone": "warm-carioca-golden-hour"
  },
  "byline": "Written by Erin Rose",
  "sections": [
    "hero",
    "quick_facts",
    "story",
    "spike_deep_explainer",
    "timeline",
    "place_anatomy",
    "day_in_life",
    "culture",
    "honest_reckoning",
    "comparison",
    "sea_surf",
    "things_to_know",
    "plan_stack",
    "spokes",
    "gallery",
    "sources"
  ],
  "spokes": [
    {
      "slug": "travel",
      "type": "audience_guide"
    },
    {
      "slug": "culture",
      "type": "deep_dive"
    }
  ],
  "adaptive": true
}